polyscience/__init__.py
polyscience/udp.py
polyscience-0.1.16.dist-info/LICENSE
polyscience-0.1.16.dist-info/METADATA
polyscience-0.1.16.dist-info/WHEEL
polyscience-0.1.16.dist-info/entry_points.txt
polyscience-0.1.16.dist-info/top_level.txt
polyscience-0.1.16.dist-info/RECORD
