Metadata-Version: 2.1
Name: polyscience
Version: 0.1.16
Summary: Python driver for Polyscience circulating baths.
Home-page: http://github.com/numat/polyscience/
Author: Patrick Fuller
Author-email: pat@numat-tech.com
License: GPLv2
Platform: UNKNOWN
Classifier: License :: OSI Approved :: GNU General Public License v2 (GPLv2)
Classifier: Development Status :: 7 - Inactive
Classifier: Natural Language :: English
Classifier: Programming Language :: Python
Classifier: Programming Language :: Python :: 2
Classifier: Programming Language :: Python :: 3
Classifier: Topic :: Scientific/Engineering :: Human Machine Interfaces
Classifier: Topic :: Scientific/Engineering :: Electronic Design Automation (EDA)
